_numpy_minmax.pyd
numpy_minmax/__init__.py
numpy_minmax/_minmax.c
numpy_minmax/_minmax_cffi.py
numpy_minmax/_version.py
numpy_minmax-0.5.0.dist-info/licenses/LICENSE
numpy_minmax-0.5.0.dist-info/METADATA
numpy_minmax-0.5.0.dist-info/WHEEL
numpy_minmax-0.5.0.dist-info/top_level.txt
numpy_minmax-0.5.0.dist-info/RECORD
